README.md
setup.py
uhm/__init__.py
uhm/deuhm.py
uhm.egg-info/PKG-INFO
uhm.egg-info/SOURCES.txt
uhm.egg-info/dependency_links.txt
uhm.egg-info/entry_points.txt
uhm.egg-info/not-zip-safe
uhm.egg-info/requires.txt
uhm.egg-info/top_level.txt