Metadata-Version: 1.2
Name: uhm
Version: 0.0.4
Summary: Code to remove filler words from videos
Home-page: UNKNOWN
Author: Adam Moss
License: MIT
Project-URL: Source, https://github.com/adammoss/uhm
Project-URL: Tracker, https://github.com/adammoss/uhm/issues
Project-URL: Licensing, https://github.com/adammoss/uhm/blob/master/LICENCE.txt
Platform: UNKNOWN
Classifier: Development Status :: 1 - Planning
Classifier: Operating System :: OS Independent
Classifier: Environment :: Console
Classifier: Intended Audience :: Science/Research
Classifier: Topic :: Scientific/Engineering :: Astronomy
Classifier: License :: OSI Approved :: GNU Lesser General Public License v3 (LGPLv3)
Classifier: Programming Language :: Python :: 3.6
Classifier: Programming Language :: Python :: 3.7
Classifier: Programming Language :: Python :: 3.8
Requires-Python: >=3.6.1
